kitcore/__init__.py
kitcore/decision_tree.py
kitcore/knn.py
kitcore/linear_regression.py
kitcore/logistic_regression.py
kitcore/multivariate_regression.py
kitcore/randomforest.py
kitcore-1.1.6.dist-info/LICENSE
kitcore-1.1.6.dist-info/METADATA
kitcore-1.1.6.dist-info/WHEEL
kitcore-1.1.6.dist-info/top_level.txt
kitcore-1.1.6.dist-info/RECORD
