Metadata-Version: 2.1
Name: kitcore
Version: 1.1.6
Summary: A short description of the package
Home-page: https://github.com/bhanupriya03m/kitcore
Author: bhanu_2025abc
Author-email: citbhanupriya@gmail.com
Classifier: Programming Language :: Python :: 3
Classifier: License :: OSI Approved :: MIT License
Classifier: Operating System :: OS Independent
Requires-Python: >=3.12
License-File: LICENSE
